franklab_mstaggedcuration/__init__.py
franklab_mstaggedcuration/p_add_curation_tags.py
franklab_mstaggedcuration/p_merge_burst_parents.py
franklab_mstaggedcuration/tagged_curation.mp
franklab_mstaggedcuration/tagged_curation.py
franklab_mstaggedcuration-0.1.3.dev0.dist-info/METADATA
franklab_mstaggedcuration-0.1.3.dev0.dist-info/WHEEL
franklab_mstaggedcuration-0.1.3.dev0.dist-info/top_level.txt
franklab_mstaggedcuration-0.1.3.dev0.dist-info/RECORD
