Metadata-Version: 2.1
Name: franklab-mstaggedcuration
Version: 0.1.3.dev0
Summary: UNKNOWN
Home-page: UNKNOWN
Author: UNKNOWN
Author-email: UNKNOWN
License: UNKNOWN
Platform: UNKNOWN
Requires-Dist: numpy
